py42195/__init__.py
py42195/config.py
py42195/constants.py
py42195/types.py
py42195/utils.py
py42195-0.1.4.dist-info/LICENSE
py42195-0.1.4.dist-info/METADATA
py42195-0.1.4.dist-info/WHEEL
py42195-0.1.4.dist-info/top_level.txt
py42195-0.1.4.dist-info/RECORD
