Metadata-Version: 2.1
Name: py42195
Version: 0.1.4
Author-email: Jan Pipek <jan.pipek@gmail.com>
License: MIT License
Project-URL: Homepage, https://github.com/janpipek/py42195
Requires-Python: >=3.11
License-File: LICENSE
Provides-Extra: dev
Requires-Dist: pytest ; extra == 'dev'
Requires-Dist: mypy ; extra == 'dev'
